BanglaProcess/__init__.py
BanglaProcess/bn_stopwords.txt
BanglaProcess-0.2.dist-info/LICENSE
BanglaProcess-0.2.dist-info/METADATA
BanglaProcess-0.2.dist-info/WHEEL
BanglaProcess-0.2.dist-info/top_level.txt
BanglaProcess-0.2.dist-info/RECORD
