Metadata-Version: 2.1
Name: BanglaProcess
Version: 0.2
Summary: UNKNOWN
Home-page: UNKNOWN
Author: Avishek Das
Author-email: avishek.das.ayan@gmail.com
License: MIT
Platform: UNKNOWN
Classifier: Programming Language :: Python :: 3
Classifier: License :: OSI Approved :: MIT License
Classifier: Operating System :: OS Independent
License-File: LICENSE
